freefft/__init__.py
freefft/__main__.py
freefft/fast_fourier_transform.py
freefft/resources_rc.py
freefft/statusbar_Vline.py
freefft/themes.py
freefft/ui_about.py
freefft/ui_about_win.py
freefft/ui_main.py
freefft-0.0.8.dist-info/LICENSE
freefft-0.0.8.dist-info/METADATA
freefft-0.0.8.dist-info/WHEEL
freefft-0.0.8.dist-info/entry_points.txt
freefft-0.0.8.dist-info/top_level.txt
freefft-0.0.8.dist-info/RECORD
