Metadata-Version: 2.1
Name: freefft
Version: 0.0.8
Summary: Fast Fourier Transform (FFT) analyzer and condition monitoring software.
Home-page: https://github.com/fjpereny/freeFFT
Author: Frank Pereny
Author-email: fjpereny@gmail.com
License: UNKNOWN
Project-URL: Homepage, https://www.frankpereny.com/freefft/
Project-URL: Git Repository, https://github.com/fjpereny/freeFFT
Project-URL: Bug Reporting, https://github.com/fjpereny/freeFFT/issues
Keywords: free fft freefft vibration condition monitoring fast fourier transform signal analysis
Platform: UNKNOWN
Classifier: Programming Language :: Python :: 3
Classifier: License :: OSI Approved :: GNU General Public License v3 (GPLv3)
Classifier: Operating System :: OS Independent
Requires-Python: >=3.6
License-File: LICENSE
Requires-Dist: numpy
Requires-Dist: scipy
Requires-Dist: pandas
Requires-Dist: pyqtgraph
Requires-Dist: PyQt5
